pypxcryptokit/__init__.py
pypxcryptokit/double_ratchet.py
pypxcryptokit/group.py
pypxcryptokit/ik.py
pypxcryptokit/sender_key_pb2.py
pypxcryptokit/sender_keys.py
pypxcryptokit/x3dh.py
pypxcryptokit-1.5.0.dist-info/METADATA
pypxcryptokit-1.5.0.dist-info/WHEEL
pypxcryptokit-1.5.0.dist-info/top_level.txt
pypxcryptokit-1.5.0.dist-info/RECORD
